whoami/__init__.py
whoami/whoami.py
whoami-2.1.8.dist-info/LICENSE
whoami-2.1.8.dist-info/METADATA
whoami-2.1.8.dist-info/WHEEL
whoami-2.1.8.dist-info/top_level.txt
whoami-2.1.8.dist-info/RECORD
