Metadata-Version: 2.1
Name: whoami
Version: 2.1.8
Summary: ✔ A convenient library to get our ip (real public ip or private ip).
Home-page: https://github.com/wangbohan2000/whoami
Author: Bohan Wang
Author-email: wbhan_cn@qq.com
License: UNKNOWN
Platform: UNKNOWN
Classifier: Programming Language :: Python :: 3
Classifier: License :: OSI Approved :: MIT License
Classifier: Operating System :: OS Independent
